MANIFEST.in
README.md
logo.png
setup.py
prime_printer/__init__.py
prime_printer/cio_helper.py
prime_printer.egg-info/PKG-INFO
prime_printer.egg-info/SOURCES.txt
prime_printer.egg-info/dependency_links.txt
prime_printer.egg-info/requires.txt
prime_printer.egg-info/top_level.txt
prime_printer/sounds/typing_1.wav
prime_printer/sounds/typing_15.wav
prime_printer/sounds/typing_16.wav
prime_printer/sounds/typing_3.wav
prime_printer/sounds/typing_4.wav
prime_printer/sounds/typing_5.wav
prime_printer/sounds/typing_7.wav
prime_printer/sounds/typing_8.wav
prime_printer/sounds/typing_9.wav
res/example_colored_delay_sound_print.gif
res/example_game_menu.gif
res/example_image_print.gif
res/example_input_with_condition.gif
res/example_progress_bar_1.gif
res/example_progress_bar_2.gif
res/example_progress_bar_3.gif