Metadata-Version: 2.4
Name: prime_printer
Version: 0.1.5
Summary: Console I/O Helper - Print Awesome. Make It Prime.
Home-page: https://github.com//prime_printer
Download-URL: https://github.com//prime_printer/archive/refs/tags/v_08.zip
Author: Tobia Ippolito
License: MIT
Keywords: Printing,Helper
Classifier: Development Status :: 4 - Beta
Classifier: Intended Audience :: Developers
Classifier: Topic :: Software Development :: Build Tools
Classifier: Programming Language :: Python :: 3.7
Classifier: Programming Language :: Python :: 3.8
Classifier: Programming Language :: Python :: 3.9
Classifier: Programming Language :: Python :: 3.10
Classifier: Programming Language :: Python :: 3.11
Classifier: Programming Language :: Python :: 3.12
Classifier: Programming Language :: Python :: 3.13
Requires-Dist: climage
Requires-Dist: pygame
Requires-Dist: opencv-python
Requires-Dist: numpy
Requires-Dist: matplotlib
Requires-Dist: IPython
Requires-Dist: psutil
Requires-Dist: gputil
Requires-Dist: py-cpuinfo
Requires-Dist: setuptools
Requires-Dist: sympy
Dynamic: author
Dynamic: classifier
Dynamic: description
Dynamic: description-content-type
Dynamic: download-url
Dynamic: home-page
Dynamic: keywords
Dynamic: license
Dynamic: requires-dist
Dynamic: summary
